{
  "generated_local": "2026-06-02T10:55:24.148652+02:00",
  "spec_version": "v1",
  "assets": [
    {
      "ticker": "UTEN",
      "display_name": "10yr UST",
      "symbol_label": "UTEN",
      "category_title": "0. Renter & Spreads",
      "is_52w_high": false,
      "is_52w_low": false,
      "52w_high": 44.38882827758789,
      "52w_low": 41.151344299316406,
      "dist_to_36WMA": null,
      "dist_to_36MMA": null,
      "weekly_close_count_above_36WMA": null,
      "gdx_gld_ratio_vs_50dma": null,
      "sil_slv_ratio_vs_50dma": null,
      "vol20_up_ok": null,
      "frames": {
        "hourly": {
          "close_above_sma36": null,
          "dist_to_36MA": null,
          "rsi14": null,
          "macd": null,
          "macd_signal": null,
          "macd_hist": null,
          "macd_cross": null
        },
        "daily": {
          "close_above_sma36": false,
          "dist_to_36MA": -0.0006508813605977752,
          "rsi14": 52.77194603241053,
          "macd": -0.05865921524959816,
          "macd_signal": -0.11513663686905333,
          "macd_hist": 0.05647742161945517,
          "macd_cross": false
        },
        "weekly": {
          "close_above_sma36": false,
          "dist_to_36MA": -0.005448487469455386,
          "rsi14": 48.94220007109846,
          "macd": -0.027430484092171525,
          "macd_signal": 0.05260944364298824,
          "macd_hist": -0.08003992773515976,
          "macd_cross": false
        },
        "monthly": {
          "close_above_sma36": true,
          "dist_to_36MA": 0.041391808601827985,
          "rsi14": 49.605629435358566,
          "macd": 0.6718296940408806,
          "macd_signal": 0.669983249801689,
          "macd_hist": 0.001846444239191558,
          "macd_cross": false
        }
      }
    },
    {
      "ticker": "2S10S",
      "display_name": "2s10s kurve",
      "symbol_label": "FRED",
      "category_title": "0. Renter & Spreads",
      "is_52w_high": false,
      "is_52w_low": false,
      "52w_high": 0.7399999999999998,
      "52w_low": 0.4299999999999997,
      "dist_to_36WMA": null,
      "dist_to_36MMA": null,
      "weekly_close_count_above_36WMA": null,
      "gdx_gld_ratio_vs_50dma": null,
      "sil_slv_ratio_vs_50dma": null,
      "vol20_up_ok": null,
      "frames": {
        "hourly": {
          "close_above_sma36": null,
          "dist_to_36MA": null,
          "rsi14": null,
          "macd": null,
          "macd_signal": null,
          "macd_hist": null,
          "macd_cross": null
        },
        "daily": {
          "close_above_sma36": false,
          "dist_to_36MA": -0.06364139457664593,
          "rsi14": 45.91950075905726,
          "macd": -0.012106098096177687,
          "macd_signal": -0.01042126354019889,
          "macd_hist": -0.0016848345559787974,
          "macd_cross": false
        },
        "weekly": {
          "close_above_sma36": false,
          "dist_to_36MA": -0.18181818181818146,
          "rsi14": 42.42638136454913,
          "macd": -0.030167110092434224,
          "macd_signal": -0.014903967592041305,
          "macd_hist": -0.015263142500392918,
          "macd_cross": false
        },
        "monthly": {
          "close_above_sma36": true,
          "dist_to_36MA": 4.584158415841584,
          "rsi14": 55.13202434602131,
          "macd": 0.15975980477479068,
          "macd_signal": 0.1821964368767956,
          "macd_hist": -0.022436632102004916,
          "macd_cross": false
        }
      }
    },
    {
      "ticker": "SCHP",
      "display_name": "10yr realrente",
      "symbol_label": "SCHP",
      "category_title": "0. Renter & Spreads",
      "is_52w_high": false,
      "is_52w_low": false,
      "52w_high": 26.656774520874023,
      "52w_low": 25.210803985595703,
      "dist_to_36WMA": null,
      "dist_to_36MMA": null,
      "weekly_close_count_above_36WMA": null,
      "gdx_gld_ratio_vs_50dma": null,
      "sil_slv_ratio_vs_50dma": null,
      "vol20_up_ok": null,
      "frames": {
        "hourly": {
          "close_above_sma36": null,
          "dist_to_36MA": null,
          "rsi14": null,
          "macd": null,
          "macd_signal": null,
          "macd_hist": null,
          "macd_cross": null
        },
        "daily": {
          "close_above_sma36": true,
          "dist_to_36MA": 0.00322373467878437,
          "rsi14": 59.45785995385961,
          "macd": 0.016171007192621545,
          "macd_signal": 0.004051696402808426,
          "macd_hist": 0.012119310789813119,
          "macd_cross": false
        },
        "weekly": {
          "close_above_sma36": true,
          "dist_to_36MA": 0.010119984349407002,
          "rsi14": 60.021381898582945,
          "macd": 0.11307625392507603,
          "macd_signal": 0.11519797893998869,
          "macd_hist": -0.0021217250149126593,
          "macd_cross": false
        },
        "monthly": {
          "close_above_sma36": true,
          "dist_to_36MA": 0.06377573409887997,
          "rsi14": 67.0668687078643,
          "macd": 0.5567047558691627,
          "macd_signal": 0.5350333902338027,
          "macd_hist": 0.021671365635359985,
          "macd_cross": false
        }
      }
    },
    {
      "ticker": "TLT",
      "display_name": "20yr UST",
      "symbol_label": "TLT",
      "category_title": "0. Renter & Spreads",
      "is_52w_high": false,
      "is_52w_low": false,
      "52w_high": 89.47512817382812,
      "52w_low": 81.30186462402344,
      "dist_to_36WMA": null,
      "dist_to_36MMA": null,
      "weekly_close_count_above_36WMA": null,
      "gdx_gld_ratio_vs_50dma": null,
      "sil_slv_ratio_vs_50dma": null,
      "vol20_up_ok": null,
      "frames": {
        "hourly": {
          "close_above_sma36": null,
          "dist_to_36MA": null,
          "rsi14": null,
          "macd": null,
          "macd_signal": null,
          "macd_hist": null,
          "macd_cross": null
        },
        "daily": {
          "close_above_sma36": true,
          "dist_to_36MA": 0.0034898199325789636,
          "rsi14": 55.634204220448304,
          "macd": -0.10989854217017125,
          "macd_signal": -0.33566603048313554,
          "macd_hist": 0.22576748831296428,
          "macd_cross": false
        },
        "weekly": {
          "close_above_sma36": false,
          "dist_to_36MA": -0.010815660549274056,
          "rsi14": 48.78684503048149,
          "macd": -0.3170387164790043,
          "macd_signal": -0.1655107983217356,
          "macd_hist": -0.15152791815726868,
          "macd_cross": false
        },
        "monthly": {
          "close_above_sma36": true,
          "dist_to_36MA": 0.003403172768598896,
          "rsi14": 47.610676237885116,
          "macd": -0.7845387381373428,
          "macd_signal": -1.171382060574501,
          "macd_hist": 0.38684332243715813,
          "macd_cross": false
        }
      }
    },
    {
      "ticker": "HYG",
      "display_name": "High Yield",
      "symbol_label": "HYG",
      "category_title": "0. Renter & Spreads",
      "is_52w_high": true,
      "is_52w_low": false,
      "52w_high": 79.9010009765625,
      "52w_low": 74.66959381103516,
      "dist_to_36WMA": null,
      "dist_to_36MMA": null,
      "weekly_close_count_above_36WMA": null,
      "gdx_gld_ratio_vs_50dma": null,
      "sil_slv_ratio_vs_50dma": null,
      "vol20_up_ok": null,
      "frames": {
        "hourly": {
          "close_above_sma36": null,
          "dist_to_36MA": null,
          "rsi14": null,
          "macd": null,
          "macd_signal": null,
          "macd_hist": null,
          "macd_cross": null
        },
        "daily": {
          "close_above_sma36": true,
          "dist_to_36MA": 0.003707026716819694,
          "rsi14": 58.1891635515917,
          "macd": 0.12452908663588858,
          "macd_signal": 0.08492375655136601,
          "macd_hist": 0.039605330084522564,
          "macd_cross": false
        },
        "weekly": {
          "close_above_sma36": true,
          "dist_to_36MA": 0.01520711303533498,
          "rsi14": 62.23252260857905,
          "macd": 0.49896704917658496,
          "macd_signal": 0.48720806984950643,
          "macd_hist": 0.011758979327078534,
          "macd_cross": false
        },
        "monthly": {
          "close_above_sma36": true,
          "dist_to_36MA": 0.10210018287762149,
          "rsi14": 77.17013201979714,
          "macd": 2.9175441115542213,
          "macd_signal": 2.9877355781750192,
          "macd_hist": -0.0701914666207979,
          "macd_cross": false
        }
      }
    },
    {
      "ticker": "LQD",
      "display_name": "IG Kreditt",
      "symbol_label": "LQD",
      "category_title": "0. Renter & Spreads",
      "is_52w_high": false,
      "is_52w_low": false,
      "52w_high": 110.0312271118164,
      "52w_low": 102.20573425292969,
      "dist_to_36WMA": null,
      "dist_to_36MMA": null,
      "weekly_close_count_above_36WMA": null,
      "gdx_gld_ratio_vs_50dma": null,
      "sil_slv_ratio_vs_50dma": null,
      "vol20_up_ok": null,
      "frames": {
        "hourly": {
          "close_above_sma36": null,
          "dist_to_36MA": null,
          "rsi14": null,
          "macd": null,
          "macd_signal": null,
          "macd_hist": null,
          "macd_cross": null
        },
        "daily": {
          "close_above_sma36": true,
          "dist_to_36MA": 0.00502151736552181,
          "rsi14": 58.50395363818147,
          "macd": 0.09286990137469786,
          "macd_signal": -0.0552781160044893,
          "macd_hist": 0.14814801737918715,
          "macd_cross": false
        },
        "weekly": {
          "close_above_sma36": true,
          "dist_to_36MA": 0.005023360658730732,
          "rsi14": 54.74422603471309,
          "macd": 0.24820717986223428,
          "macd_signal": 0.289379998327317,
          "macd_hist": -0.041172818465082694,
          "macd_cross": false
        },
        "monthly": {
          "close_above_sma36": true,
          "dist_to_36MA": 0.06865171274025324,
          "rsi14": 62.201214499706005,
          "macd": 2.5127045700751864,
          "macd_signal": 2.471975292772736,
          "macd_hist": 0.04072927730245057,
          "macd_cross": false
        }
      }
    },
    {
      "ticker": "SPY",
      "display_name": "S&P 500",
      "symbol_label": "SPY",
      "category_title": "1. Aksjer",
      "is_52w_high": true,
      "is_52w_low": false,
      "52w_high": 758.5399780273438,
      "52w_low": 582.7101440429688,
      "dist_to_36WMA": null,
      "dist_to_36MMA": null,
      "weekly_close_count_above_36WMA": null,
      "gdx_gld_ratio_vs_50dma": null,
      "sil_slv_ratio_vs_50dma": null,
      "vol20_up_ok": null,
      "frames": {
        "hourly": {
          "close_above_sma36": null,
          "dist_to_36MA": null,
          "rsi14": null,
          "macd": null,
          "macd_signal": null,
          "macd_hist": null,
          "macd_cross": null
        },
        "daily": {
          "close_above_sma36": true,
          "dist_to_36MA": 0.045440506283184884,
          "rsi14": 75.1838896647595,
          "macd": 12.852951574493659,
          "macd_signal": 12.918305523114087,
          "macd_hist": -0.06535394862042843,
          "macd_cross": false
        },
        "weekly": {
          "close_above_sma36": true,
          "dist_to_36MA": 0.10394859221011996,
          "rsi14": 74.02083166401995,
          "macd": 23.382604171805383,
          "macd_signal": 16.1405798719656,
          "macd_hist": 7.242024299839784,
          "macd_cross": false
        },
        "monthly": {
          "close_above_sma36": true,
          "dist_to_36MA": 0.3192886887870533,
          "rsi14": 76.75145504327972,
          "macd": 60.16108470129507,
          "macd_signal": 54.52602429626741,
          "macd_hist": 5.635060405027659,
          "macd_cross": false
        }
      }
    },
    {
      "ticker": "QQQ",
      "display_name": "Nasdaq-100",
      "symbol_label": "QQQ",
      "category_title": "1. Aksjer",
      "is_52w_high": true,
      "is_52w_low": false,
      "52w_high": 742.739990234375,
      "52w_low": 516.609375,
      "dist_to_36WMA": null,
      "dist_to_36MMA": null,
      "weekly_close_count_above_36WMA": null,
      "gdx_gld_ratio_vs_50dma": null,
      "sil_slv_ratio_vs_50dma": null,
      "vol20_up_ok": null,
      "frames": {
        "hourly": {
          "close_above_sma36": null,
          "dist_to_36MA": null,
          "rsi14": null,
          "macd": null,
          "macd_signal": null,
          "macd_hist": null,
          "macd_cross": null
        },
        "daily": {
          "close_above_sma36": true,
          "dist_to_36MA": 0.08605669157790694,
          "rsi14": 78.4397378342893,
          "macd": 21.759685986999898,
          "macd_signal": 21.524142416736584,
          "macd_hist": 0.23554357026331374,
          "macd_cross": false
        },
        "weekly": {
          "close_above_sma36": true,
          "dist_to_36MA": 0.18337765231415137,
          "rsi14": 77.94082976161019,
          "macd": 35.25464016540491,
          "macd_signal": 22.29272211236674,
          "macd_hist": 12.961918053038168,
          "macd_cross": false
        },
        "monthly": {
          "close_above_sma36": true,
          "dist_to_36MA": 0.45715744367990924,
          "rsi14": 78.47074777527101,
          "macd": 68.9534602636503,
          "macd_signal": 58.0888367765911,
          "macd_hist": 10.864623487059198,
          "macd_cross": false
        }
      }
    },
    {
      "ticker": "IWM",
      "display_name": "Russell 2000",
      "symbol_label": "IWM",
      "category_title": "1. Aksjer",
      "is_52w_high": false,
      "is_52w_low": false,
      "52w_high": 292.0299987792969,
      "52w_low": 202.88365173339844,
      "dist_to_36WMA": null,
      "dist_to_36MMA": null,
      "weekly_close_count_above_36WMA": null,
      "gdx_gld_ratio_vs_50dma": null,
      "sil_slv_ratio_vs_50dma": null,
      "vol20_up_ok": null,
      "frames": {
        "hourly": {
          "close_above_sma36": null,
          "dist_to_36MA": null,
          "rsi14": null,
          "macd": null,
          "macd_signal": null,
          "macd_hist": null,
          "macd_cross": null
        },
        "daily": {
          "close_above_sma36": true,
          "dist_to_36MA": 0.03554794354367172,
          "rsi14": 61.60391611681924,
          "macd": 4.735035137210616,
          "macd_signal": 4.454437739860331,
          "macd_hist": 0.2805973973502853,
          "macd_cross": false
        },
        "weekly": {
          "close_above_sma36": true,
          "dist_to_36MA": 0.12105748522886335,
          "rsi14": 68.92835801612247,
          "macd": 11.113951579581055,
          "macd_signal": 8.866347696299574,
          "macd_hist": 2.2476038832814815,
          "macd_cross": false
        },
        "monthly": {
          "close_above_sma36": true,
          "dist_to_36MA": 0.319754981446575,
          "rsi14": 70.9664732389731,
          "macd": 21.107915784330828,
          "macd_signal": 16.034591205390406,
          "macd_hist": 5.073324578940422,
          "macd_cross": false
        }
      }
    },
    {
      "ticker": "ACWI",
      "display_name": "ACWI",
      "symbol_label": "ACWI",
      "category_title": "1. Aksjer",
      "is_52w_high": true,
      "is_52w_low": false,
      "52w_high": 159.10000610351562,
      "52w_low": 121.63367462158203,
      "dist_to_36WMA": null,
      "dist_to_36MMA": null,
      "weekly_close_count_above_36WMA": null,
      "gdx_gld_ratio_vs_50dma": null,
      "sil_slv_ratio_vs_50dma": null,
      "vol20_up_ok": null,
      "frames": {
        "hourly": {
          "close_above_sma36": null,
          "dist_to_36MA": null,
          "rsi14": null,
          "macd": null,
          "macd_signal": null,
          "macd_hist": null,
          "macd_cross": null
        },
        "daily": {
          "close_above_sma36": true,
          "dist_to_36MA": 0.041402689190643556,
          "rsi14": 69.2468607063194,
          "macd": 2.4252028367259584,
          "macd_signal": 2.3552034386231533,
          "macd_hist": 0.06999939810280509,
          "macd_cross": false
        },
        "weekly": {
          "close_above_sma36": true,
          "dist_to_36MA": 0.10328928302346378,
          "rsi14": 72.18739335201933,
          "macd": 4.950250996169615,
          "macd_signal": 3.759605552168252,
          "macd_hist": 1.1906454440013627,
          "macd_cross": false
        },
        "monthly": {
          "close_above_sma36": true,
          "dist_to_36MA": 0.3288058199416716,
          "rsi14": 77.3004972012202,
          "macd": 12.885413039712716,
          "macd_signal": 11.30318299047036,
          "macd_hist": 1.5822300492423569,
          "macd_cross": false
        }
      }
    },
    {
      "ticker": "EXSA",
      "display_name": "STOXX Europe 600",
      "symbol_label": "EXSA",
      "category_title": "1. Aksjer",
      "is_52w_high": false,
      "is_52w_low": false,
      "52w_high": 63.939998626708984,
      "52w_low": 52.40556335449219,
      "dist_to_36WMA": null,
      "dist_to_36MMA": null,
      "weekly_close_count_above_36WMA": null,
      "gdx_gld_ratio_vs_50dma": null,
      "sil_slv_ratio_vs_50dma": null,
      "vol20_up_ok": null,
      "frames": {
        "hourly": {
          "close_above_sma36": null,
          "dist_to_36MA": null,
          "rsi14": null,
          "macd": null,
          "macd_signal": null,
          "macd_hist": null,
          "macd_cross": null
        },
        "daily": {
          "close_above_sma36": true,
          "dist_to_36MA": 0.02058219362185128,
          "rsi14": 58.151862284777366,
          "macd": 0.5871990310617434,
          "macd_signal": 0.5612367895104473,
          "macd_hist": 0.025962241551296117,
          "macd_cross": false
        },
        "weekly": {
          "close_above_sma36": true,
          "dist_to_36MA": 0.06372238226855445,
          "rsi14": 62.97334904256017,
          "macd": 1.314634069014211,
          "macd_signal": 1.1974713771650578,
          "macd_hist": 0.11716269184915329,
          "macd_cross": false
        },
        "monthly": {
          "close_above_sma36": true,
          "dist_to_36MA": 0.2216660651290427,
          "rsi14": 70.4763161374124,
          "macd": 4.028258403158901,
          "macd_signal": 3.6143500596264677,
          "macd_hist": 0.41390834353243333,
          "macd_cross": false
        }
      }
    },
    {
      "ticker": "EEM",
      "display_name": "MSCI EM",
      "symbol_label": "EEM",
      "category_title": "1. Aksjer",
      "is_52w_high": true,
      "is_52w_low": false,
      "52w_high": 70.08000183105469,
      "52w_low": 44.44718933105469,
      "dist_to_36WMA": null,
      "dist_to_36MMA": null,
      "weekly_close_count_above_36WMA": null,
      "gdx_gld_ratio_vs_50dma": null,
      "sil_slv_ratio_vs_50dma": null,
      "vol20_up_ok": null,
      "frames": {
        "hourly": {
          "close_above_sma36": null,
          "dist_to_36MA": null,
          "rsi14": null,
          "macd": null,
          "macd_signal": null,
          "macd_hist": null,
          "macd_cross": null
        },
        "daily": {
          "close_above_sma36": true,
          "dist_to_36MA": 0.07812162472049684,
          "rsi14": 69.21921731751743,
          "macd": 1.5441009484605104,
          "macd_signal": 1.3711268704563557,
          "macd_hist": 0.17297407800415465,
          "macd_cross": false
        },
        "weekly": {
          "close_above_sma36": true,
          "dist_to_36MA": 0.1993828330681575,
          "rsi14": 72.73875865492163,
          "macd": 3.573625551566508,
          "macd_signal": 2.8681242057171943,
          "macd_hist": 0.7055013458493136,
          "macd_cross": false
        },
        "monthly": {
          "close_above_sma36": true,
          "dist_to_36MA": 0.5181513928689021,
          "rsi14": 78.41808091001775,
          "macd": 6.715507798319869,
          "macd_signal": 4.892722811586964,
          "macd_hist": 1.8227849867329056,
          "macd_cross": false
        }
      }
    },
    {
      "ticker": "VNQ",
      "display_name": "Housing US",
      "symbol_label": "VNQ",
      "category_title": "1. Aksjer",
      "is_52w_high": false,
      "is_52w_low": false,
      "52w_high": 97.22000122070312,
      "52w_low": 85.7279052734375,
      "dist_to_36WMA": null,
      "dist_to_36MMA": null,
      "weekly_close_count_above_36WMA": null,
      "gdx_gld_ratio_vs_50dma": null,
      "sil_slv_ratio_vs_50dma": null,
      "vol20_up_ok": null,
      "frames": {
        "hourly": {
          "close_above_sma36": null,
          "dist_to_36MA": null,
          "rsi14": null,
          "macd": null,
          "macd_signal": null,
          "macd_hist": null,
          "macd_cross": null
        },
        "daily": {
          "close_above_sma36": false,
          "dist_to_36MA": -0.01606661772193984,
          "rsi14": 41.9266611150872,
          "macd": 0.3469857573271895,
          "macd_signal": 0.5979073864773027,
          "macd_hist": -0.2509216291501132,
          "macd_cross": false
        },
        "weekly": {
          "close_above_sma36": true,
          "dist_to_36MA": 0.03418290687080421,
          "rsi14": 53.73929176649261,
          "macd": 1.6615187267461948,
          "macd_signal": 1.516533513965959,
          "macd_hist": 0.1449852127802358,
          "macd_cross": false
        },
        "monthly": {
          "close_above_sma36": true,
          "dist_to_36MA": 0.1126616322036153,
          "rsi14": 57.76168390090714,
          "macd": 3.2353914179684153,
          "macd_signal": 2.8613817194009217,
          "macd_hist": 0.37400969856749366,
          "macd_cross": false
        }
      }
    },
    {
      "ticker": "IAI",
      "display_name": "Broker/Dealers",
      "symbol_label": "IAI",
      "category_title": "1. Aksjer",
      "is_52w_high": false,
      "is_52w_low": false,
      "52w_high": 189.59327697753906,
      "52w_low": 152.2912139892578,
      "dist_to_36WMA": null,
      "dist_to_36MMA": null,
      "weekly_close_count_above_36WMA": null,
      "gdx_gld_ratio_vs_50dma": null,
      "sil_slv_ratio_vs_50dma": null,
      "vol20_up_ok": null,
      "frames": {
        "hourly": {
          "close_above_sma36": null,
          "dist_to_36MA": null,
          "rsi14": null,
          "macd": null,
          "macd_signal": null,
          "macd_hist": null,
          "macd_cross": null
        },
        "daily": {
          "close_above_sma36": true,
          "dist_to_36MA": 0.034158592764547364,
          "rsi14": 64.99182714375584,
          "macd": 1.7478318344608965,
          "macd_signal": 1.4961722932943466,
          "macd_hist": 0.25165954116654987,
          "macd_cross": false
        },
        "weekly": {
          "close_above_sma36": true,
          "dist_to_36MA": 0.05076799902201911,
          "rsi14": 61.1874106552836,
          "macd": 2.362616612610907,
          "macd_signal": 1.0813465689058643,
          "macd_hist": 1.2812700437050426,
          "macd_cross": false
        },
        "monthly": {
          "close_above_sma36": true,
          "dist_to_36MA": 0.3160201406758345,
          "rsi14": 67.81781832043467,
          "macd": 16.013324785834698,
          "macd_signal": 16.792136832138,
          "macd_hist": -0.778812046303301,
          "macd_cross": false
        }
      }
    },
    {
      "ticker": "SOXQ",
      "display_name": "Semiconductors",
      "symbol_label": "SOXQ",
      "category_title": "2. Tech & Halvledere",
      "is_52w_high": true,
      "is_52w_low": false,
      "52w_high": 102.02999877929688,
      "52w_low": 37.26066589355469,
      "dist_to_36WMA": null,
      "dist_to_36MMA": null,
      "weekly_close_count_above_36WMA": null,
      "gdx_gld_ratio_vs_50dma": null,
      "sil_slv_ratio_vs_50dma": null,
      "vol20_up_ok": null,
      "frames": {
        "hourly": {
          "close_above_sma36": null,
          "dist_to_36MA": null,
          "rsi14": null,
          "macd": null,
          "macd_signal": null,
          "macd_hist": null,
          "macd_cross": null
        },
        "daily": {
          "close_above_sma36": true,
          "dist_to_36MA": 0.1813357369699164,
          "rsi14": 73.2692998315157,
          "macd": 5.9557082049301755,
          "macd_signal": 5.738624882812584,
          "macd_hist": 0.21708332211759185,
          "macd_cross": false
        },
        "weekly": {
          "close_above_sma36": true,
          "dist_to_36MA": 0.5556752788271255,
          "rsi14": 86.5904410331618,
          "macd": 11.400932395595007,
          "macd_signal": 8.184220705440097,
          "macd_hist": 3.2167116901549093,
          "macd_cross": false
        },
        "monthly": {
          "close_above_sma36": true,
          "dist_to_36MA": 1.2435834730000404,
          "rsi14": 87.5403557243553,
          "macd": 14.116941265202321,
          "macd_signal": 8.792103239611748,
          "macd_hist": 5.324838025590573,
          "macd_cross": false
        }
      }
    },
    {
      "ticker": "HACK",
      "display_name": "Cybersecurity",
      "symbol_label": "HACK",
      "category_title": "2. Tech & Halvledere",
      "is_52w_high": true,
      "is_52w_low": false,
      "52w_high": 105.0,
      "52w_low": 70.69000244140625,
      "dist_to_36WMA": null,
      "dist_to_36MMA": null,
      "weekly_close_count_above_36WMA": null,
      "gdx_gld_ratio_vs_50dma": null,
      "sil_slv_ratio_vs_50dma": null,
      "vol20_up_ok": null,
      "frames": {
        "hourly": {
          "close_above_sma36": null,
          "dist_to_36MA": null,
          "rsi14": null,
          "macd": null,
          "macd_signal": null,
          "macd_hist": null,
          "macd_cross": null
        },
        "daily": {
          "close_above_sma36": true,
          "dist_to_36MA": 0.2408902907842219,
          "rsi14": 80.51823856624561,
          "macd": 4.950465148070222,
          "macd_signal": 3.878815255375172,
          "macd_hist": 1.0716498926950502,
          "macd_cross": false
        },
        "weekly": {
          "close_above_sma36": true,
          "dist_to_36MA": 0.2771094589621862,
          "rsi14": 75.06507531911735,
          "macd": 4.1823319386681845,
          "macd_signal": 0.9662979284296616,
          "macd_hist": 3.216034010238523,
          "macd_cross": false
        },
        "monthly": {
          "close_above_sma36": true,
          "dist_to_36MA": 0.4515998656353809,
          "rsi14": 74.61560284183568,
          "macd": 6.973383170681444,
          "macd_signal": 5.919730736411166,
          "macd_hist": 1.053652434270278,
          "macd_cross": true
        }
      }
    },
    {
      "ticker": "SKYY",
      "display_name": "Cloud",
      "symbol_label": "SKYY",
      "category_title": "2. Tech & Halvledere",
      "is_52w_high": true,
      "is_52w_low": false,
      "52w_high": 155.1699981689453,
      "52w_low": 104.16000366210938,
      "dist_to_36WMA": null,
      "dist_to_36MMA": null,
      "weekly_close_count_above_36WMA": null,
      "gdx_gld_ratio_vs_50dma": null,
      "sil_slv_ratio_vs_50dma": null,
      "vol20_up_ok": null,
      "frames": {
        "hourly": {
          "close_above_sma36": null,
          "dist_to_36MA": null,
          "rsi14": null,
          "macd": null,
          "macd_signal": null,
          "macd_hist": null,
          "macd_cross": null
        },
        "daily": {
          "close_above_sma36": true,
          "dist_to_36MA": 0.2416966255454073,
          "rsi14": 85.28503005447836,
          "macd": 6.117347196646136,
          "macd_signal": 4.30874491376848,
          "macd_hist": 1.808602282877656,
          "macd_cross": false
        },
        "weekly": {
          "close_above_sma36": true,
          "dist_to_36MA": 0.23759495001755981,
          "rsi14": 73.08121196029589,
          "macd": 4.670197613284145,
          "macd_signal": 0.10858291860149671,
          "macd_hist": 4.561614694682649,
          "macd_cross": false
        },
        "monthly": {
          "close_above_sma36": true,
          "dist_to_36MA": 0.4289346459003799,
          "rsi14": 68.165017312604,
          "macd": 10.10410729216487,
          "macd_signal": 9.113107656948682,
          "macd_hist": 0.9909996352161876,
          "macd_cross": true
        }
      }
    },
    {
      "ticker": "BOTZ",
      "display_name": "Robotics/AI",
      "symbol_label": "BOTZ",
      "category_title": "2. Tech & Halvledere",
      "is_52w_high": false,
      "is_52w_low": false,
      "52w_high": 41.630001068115234,
      "52w_low": 30.24488639831543,
      "dist_to_36WMA": null,
      "dist_to_36MMA": null,
      "weekly_close_count_above_36WMA": null,
      "gdx_gld_ratio_vs_50dma": null,
      "sil_slv_ratio_vs_50dma": null,
      "vol20_up_ok": null,
      "frames": {
        "hourly": {
          "close_above_sma36": null,
          "dist_to_36MA": null,
          "rsi14": null,
          "macd": null,
          "macd_signal": null,
          "macd_hist": null,
          "macd_cross": null
        },
        "daily": {
          "close_above_sma36": true,
          "dist_to_36MA": 0.045336487419503815,
          "rsi14": 58.45637738829718,
          "macd": 0.695735118405203,
          "macd_signal": 0.8267421403847393,
          "macd_hist": -0.1310070219795363,
          "macd_cross": false
        },
        "weekly": {
          "close_above_sma36": true,
          "dist_to_36MA": 0.09759277163796873,
          "rsi14": 62.58195376715745,
          "macd": 1.2392491542275152,
          "macd_signal": 0.8286037853112532,
          "macd_hist": 0.410645368916262,
          "macd_cross": false
        },
        "monthly": {
          "close_above_sma36": true,
          "dist_to_36MA": 0.26736938202479243,
          "rsi14": 63.349997000331385,
          "macd": 2.5724199006076702,
          "macd_signal": 2.1179401562981255,
          "macd_hist": 0.45447974430954474,
          "macd_cross": false
        }
      }
    },
    {
      "ticker": "BCOM",
      "display_name": "Commodity bred",
      "symbol_label": "BCOM",
      "category_title": "3. Råvarer",
      "is_52w_high": false,
      "is_52w_low": false,
      "52w_high": 18.90999984741211,
      "52w_low": 12.071361541748047,
      "dist_to_36WMA": null,
      "dist_to_36MMA": null,
      "weekly_close_count_above_36WMA": null,
      "gdx_gld_ratio_vs_50dma": null,
      "sil_slv_ratio_vs_50dma": null,
      "vol20_up_ok": null,
      "frames": {
        "hourly": {
          "close_above_sma36": null,
          "dist_to_36MA": null,
          "rsi14": null,
          "macd": null,
          "macd_signal": null,
          "macd_hist": null,
          "macd_cross": null
        },
        "daily": {
          "close_above_sma36": false,
          "dist_to_36MA": -0.007191541427237889,
          "rsi14": 46.96935701072295,
          "macd": 0.0049089721646957685,
          "macd_signal": 0.1538360465852632,
          "macd_hist": -0.14892707442056743,
          "macd_cross": false
        },
        "weekly": {
          "close_above_sma36": true,
          "dist_to_36MA": 0.1839275318980452,
          "rsi14": 66.29166103612735,
          "macd": 1.146858510186334,
          "macd_signal": 1.1393225585177997,
          "macd_hist": 0.007535951668534269,
          "macd_cross": false
        },
        "monthly": {
          "close_above_sma36": true,
          "dist_to_36MA": 0.33360482936391644,
          "rsi14": 75.8248706725712,
          "macd": 1.2999977509130325,
          "macd_signal": 0.7360786055818124,
          "macd_hist": 0.5639191453312201,
          "macd_cross": false
        }
      }
    },
    {
      "ticker": "USO",
      "display_name": "Olje (WTI)",
      "symbol_label": "USO",
      "category_title": "3. Råvarer",
      "is_52w_high": false,
      "is_52w_low": false,
      "52w_high": 152.9600067138672,
      "52w_low": 66.16999816894531,
      "dist_to_36WMA": null,
      "dist_to_36MMA": null,
      "weekly_close_count_above_36WMA": null,
      "gdx_gld_ratio_vs_50dma": null,
      "sil_slv_ratio_vs_50dma": null,
      "vol20_up_ok": null,
      "frames": {
        "hourly": {
          "close_above_sma36": null,
          "dist_to_36MA": null,
          "rsi14": null,
          "macd": null,
          "macd_signal": null,
          "macd_hist": null,
          "macd_cross": null
        },
        "daily": {
          "close_above_sma36": false,
          "dist_to_36MA": -0.005796457734440861,
          "rsi14": 48.78023781738719,
          "macd": 0.3142688637398692,
          "macd_signal": 2.556192052373023,
          "macd_hist": -2.241923188633154,
          "macd_cross": false
        },
        "weekly": {
          "close_above_sma36": true,
          "dist_to_36MA": 0.42985280935750037,
          "rsi14": 62.22192222464335,
          "macd": 15.971827272868012,
          "macd_signal": 15.061533821586163,
          "macd_hist": 0.9102934512818486,
          "macd_cross": false
        },
        "monthly": {
          "close_above_sma36": true,
          "dist_to_36MA": 0.6735856348155678,
          "rsi14": 71.00181778202332,
          "macd": 14.289817969338301,
          "macd_signal": 7.017399556451695,
          "macd_hist": 7.272418412886607,
          "macd_cross": false
        }
      }
    },
    {
      "ticker": "UNG",
      "display_name": "Naturgass",
      "symbol_label": "UNG",
      "category_title": "3. Råvarer",
      "is_52w_high": false,
      "is_52w_low": false,
      "52w_high": 18.079999923706055,
      "52w_low": 10.149999618530273,
      "dist_to_36WMA": null,
      "dist_to_36MMA": null,
      "weekly_close_count_above_36WMA": null,
      "gdx_gld_ratio_vs_50dma": null,
      "sil_slv_ratio_vs_50dma": null,
      "vol20_up_ok": null,
      "frames": {
        "hourly": {
          "close_above_sma36": null,
          "dist_to_36MA": null,
          "rsi14": null,
          "macd": null,
          "macd_signal": null,
          "macd_hist": null,
          "macd_cross": null
        },
        "daily": {
          "close_above_sma36": true,
          "dist_to_36MA": 0.05546098417851866,
          "rsi14": 54.57840983610754,
          "macd": 0.16024511679138875,
          "macd_signal": 0.08688331493995441,
          "macd_hist": 0.07336180185143434,
          "macd_cross": false
        },
        "weekly": {
          "close_above_sma36": false,
          "dist_to_36MA": -0.07414589194476641,
          "rsi14": 47.36885060693105,
          "macd": -0.5717837061297626,
          "macd_signal": -0.6539478428895208,
          "macd_hist": 0.0821641367597582,
          "macd_cross": false
        },
        "monthly": {
          "close_above_sma36": false,
          "dist_to_36MA": -0.31192341842832283,
          "rsi14": 40.755416094735466,
          "macd": -4.1102584774011035,
          "macd_signal": -4.926732970921702,
          "macd_hist": 0.8164744935205981,
          "macd_cross": false
        }
      }
    },
    {
      "ticker": "COPX",
      "display_name": "Kobber miners",
      "symbol_label": "COPX",
      "category_title": "3. Råvarer",
      "is_52w_high": false,
      "is_52w_low": false,
      "52w_high": 95.69999694824219,
      "52w_low": 39.938167572021484,
      "dist_to_36WMA": null,
      "dist_to_36MMA": null,
      "weekly_close_count_above_36WMA": null,
      "gdx_gld_ratio_vs_50dma": null,
      "sil_slv_ratio_vs_50dma": null,
      "vol20_up_ok": null,
      "frames": {
        "hourly": {
          "close_above_sma36": null,
          "dist_to_36MA": null,
          "rsi14": null,
          "macd": null,
          "macd_signal": null,
          "macd_hist": null,
          "macd_cross": null
        },
        "daily": {
          "close_above_sma36": true,
          "dist_to_36MA": 0.07059216706023483,
          "rsi14": 60.17834014019884,
          "macd": 1.5409415968117912,
          "macd_signal": 1.0835465689675043,
          "macd_hist": 0.45739502784428687,
          "macd_cross": false
        },
        "weekly": {
          "close_above_sma36": true,
          "dist_to_36MA": 0.1963093806192152,
          "rsi14": 62.061449595435526,
          "macd": 5.058834792933581,
          "macd_signal": 5.296870486988777,
          "macd_hist": -0.23803569405519553,
          "macd_cross": false
        },
        "monthly": {
          "close_above_sma36": true,
          "dist_to_36MA": 0.8093583108582733,
          "rsi14": 71.4466220958826,
          "macd": 13.085117602407152,
          "macd_signal": 9.759117834804664,
          "macd_hist": 3.3259997676024877,
          "macd_cross": false
        }
      }
    },
    {
      "ticker": "XME",
      "display_name": "Metals/Mining",
      "symbol_label": "XME",
      "category_title": "3. Råvarer",
      "is_52w_high": false,
      "is_52w_low": false,
      "52w_high": 131.3585968017578,
      "52w_low": 59.83977508544922,
      "dist_to_36WMA": null,
      "dist_to_36MMA": null,
      "weekly_close_count_above_36WMA": null,
      "gdx_gld_ratio_vs_50dma": null,
      "sil_slv_ratio_vs_50dma": null,
      "vol20_up_ok": null,
      "frames": {
        "hourly": {
          "close_above_sma36": null,
          "dist_to_36MA": null,
          "rsi14": null,
          "macd": null,
          "macd_signal": null,
          "macd_hist": null,
          "macd_cross": null
        },
        "daily": {
          "close_above_sma36": true,
          "dist_to_36MA": 0.07231643751385246,
          "rsi14": 62.784277255222186,
          "macd": 2.024887609312401,
          "macd_signal": 1.1318521775967525,
          "macd_hist": 0.8930354317156486,
          "macd_cross": false
        },
        "weekly": {
          "close_above_sma36": true,
          "dist_to_36MA": 0.15658363719535567,
          "rsi14": 65.38289245873429,
          "macd": 5.729044371974624,
          "macd_signal": 5.587092613529824,
          "macd_hist": 0.1419517584448,
          "macd_cross": true
        },
        "monthly": {
          "close_above_sma36": true,
          "dist_to_36MA": 0.7233750585055893,
          "rsi14": 77.46409296700062,
          "macd": 17.567464435958726,
          "macd_signal": 13.666889783951483,
          "macd_hist": 3.9005746520072435,
          "macd_cross": false
        }
      }
    },
    {
      "ticker": "XLE",
      "display_name": "Energy",
      "symbol_label": "XLE",
      "category_title": "3. Råvarer",
      "is_52w_high": false,
      "is_52w_low": false,
      "52w_high": 62.560001373291016,
      "52w_low": 39.49696731567383,
      "dist_to_36WMA": null,
      "dist_to_36MMA": null,
      "weekly_close_count_above_36WMA": null,
      "gdx_gld_ratio_vs_50dma": null,
      "sil_slv_ratio_vs_50dma": null,
      "vol20_up_ok": null,
      "frames": {
        "hourly": {
          "close_above_sma36": null,
          "dist_to_36MA": null,
          "rsi14": null,
          "macd": null,
          "macd_signal": null,
          "macd_hist": null,
          "macd_cross": null
        },
        "daily": {
          "close_above_sma36": false,
          "dist_to_36MA": -0.005275506637974124,
          "rsi14": 46.729733651662805,
          "macd": -0.09372546152513195,
          "macd_signal": 0.1866475421673454,
          "macd_hist": -0.2803730036924773,
          "macd_cross": false
        },
        "weekly": {
          "close_above_sma36": true,
          "dist_to_36MA": 0.12339349854815035,
          "rsi14": 57.089990919001266,
          "macd": 2.747163344789854,
          "macd_signal": 3.168144464709277,
          "macd_hist": -0.4209811199194231,
          "macd_cross": false
        },
        "monthly": {
          "close_above_sma36": true,
          "dist_to_36MA": 0.28409742094079715,
          "rsi14": 67.47641966609973,
          "macd": 4.653320509529898,
          "macd_signal": 3.340322617811848,
          "macd_hist": 1.3129978917180503,
          "macd_cross": false
        }
      }
    },
    {
      "ticker": "DBA",
      "display_name": "Agri/mat",
      "symbol_label": "DBA",
      "category_title": "3. Råvarer",
      "is_52w_high": false,
      "is_52w_low": false,
      "52w_high": 28.729999542236328,
      "52w_low": 24.72818946838379,
      "dist_to_36WMA": null,
      "dist_to_36MMA": null,
      "weekly_close_count_above_36WMA": null,
      "gdx_gld_ratio_vs_50dma": null,
      "sil_slv_ratio_vs_50dma": null,
      "vol20_up_ok": null,
      "frames": {
        "hourly": {
          "close_above_sma36": null,
          "dist_to_36MA": null,
          "rsi14": null,
          "macd": null,
          "macd_signal": null,
          "macd_hist": null,
          "macd_cross": null
        },
        "daily": {
          "close_above_sma36": false,
          "dist_to_36MA": -0.016241491817381958,
          "rsi14": 40.64173797120751,
          "macd": -0.05593637326413514,
          "macd_signal": 0.08329037480433554,
          "macd_hist": -0.13922674806847068,
          "macd_cross": false
        },
        "weekly": {
          "close_above_sma36": true,
          "dist_to_36MA": 0.038022755606696726,
          "rsi14": 58.129072862214976,
          "macd": 0.465998785459945,
          "macd_signal": 0.4513408643752094,
          "macd_hist": 0.01465792108473557,
          "macd_cross": false
        },
        "monthly": {
          "close_above_sma36": true,
          "dist_to_36MA": 0.1382133472024139,
          "rsi14": 65.35076682563553,
          "macd": 1.3591455099405678,
          "macd_signal": 1.411580370846706,
          "macd_hist": -0.05243486090613825,
          "macd_cross": false
        }
      }
    },
    {
      "ticker": "GLD",
      "display_name": "Gull",
      "symbol_label": "GLD",
      "category_title": "4. Edelmetaller",
      "is_52w_high": false,
      "is_52w_low": false,
      "52w_high": 495.8999938964844,
      "52w_low": 300.9599914550781,
      "dist_to_36WMA": null,
      "dist_to_36MMA": null,
      "weekly_close_count_above_36WMA": null,
      "gdx_gld_ratio_vs_50dma": null,
      "sil_slv_ratio_vs_50dma": null,
      "vol20_up_ok": null,
      "frames": {
        "hourly": {
          "close_above_sma36": null,
          "dist_to_36MA": null,
          "rsi14": null,
          "macd": null,
          "macd_signal": null,
          "macd_hist": null,
          "macd_cross": null
        },
        "daily": {
          "close_above_sma36": false,
          "dist_to_36MA": -0.03517089915251019,
          "rsi14": 40.98254668957337,
          "macd": -5.0187893612987295,
          "macd_signal": -4.549962850254683,
          "macd_hist": -0.46882651104404616,
          "macd_cross": false
        },
        "weekly": {
          "close_above_sma36": false,
          "dist_to_36MA": -0.012810127378496136,
          "rsi14": 47.53988566410496,
          "macd": 5.93348191462826,
          "macd_signal": 13.3350996607247,
          "macd_hist": -7.40161774609644,
          "macd_cross": false
        },
        "monthly": {
          "close_above_sma36": true,
          "dist_to_36MA": 0.44758466688593596,
          "rsi14": 68.85906989276414,
          "macd": 54.84777230709432,
          "macd_signal": 51.4796900420685,
          "macd_hist": 3.3680822650258193,
          "macd_cross": false
        }
      }
    },
    {
      "ticker": "SLV",
      "display_name": "Solv",
      "symbol_label": "SLV",
      "category_title": "4. Edelmetaller",
      "is_52w_high": false,
      "is_52w_low": false,
      "52w_high": 105.5999984741211,
      "52w_low": 30.0,
      "dist_to_36WMA": null,
      "dist_to_36MMA": null,
      "weekly_close_count_above_36WMA": null,
      "gdx_gld_ratio_vs_50dma": null,
      "sil_slv_ratio_vs_50dma": null,
      "vol20_up_ok": null,
      "frames": {
        "hourly": {
          "close_above_sma36": null,
          "dist_to_36MA": null,
          "rsi14": null,
          "macd": null,
          "macd_signal": null,
          "macd_hist": null,
          "macd_cross": null
        },
        "daily": {
          "close_above_sma36": false,
          "dist_to_36MA": -0.033519693201852344,
          "rsi14": 45.39189226706104,
          "macd": -0.5419419876565996,
          "macd_signal": -0.07115513473232113,
          "macd_hist": -0.47078685292427846,
          "macd_cross": false
        },
        "weekly": {
          "close_above_sma36": true,
          "dist_to_36MA": 0.05641293445966252,
          "rsi14": 51.72222617574589,
          "macd": 2.8406140245383966,
          "macd_signal": 4.363778979695506,
          "macd_hist": -1.5231649551571094,
          "macd_cross": false
        },
        "monthly": {
          "close_above_sma36": true,
          "dist_to_36MA": 0.8423910155359668,
          "rsi14": 68.89417090751375,
          "macd": 12.078081342436626,
          "macd_signal": 9.840942237575803,
          "macd_hist": 2.237139104860823,
          "macd_cross": false
        }
      }
    },
    {
      "ticker": "GDX",
      "display_name": "Gull miners",
      "symbol_label": "GDX",
      "category_title": "4. Edelmetaller",
      "is_52w_high": false,
      "is_52w_low": false,
      "52w_high": 115.83999633789062,
      "52w_low": 50.28479766845703,
      "dist_to_36WMA": null,
      "dist_to_36MMA": null,
      "weekly_close_count_above_36WMA": null,
      "gdx_gld_ratio_vs_50dma": null,
      "sil_slv_ratio_vs_50dma": null,
      "vol20_up_ok": null,
      "frames": {
        "hourly": {
          "close_above_sma36": null,
          "dist_to_36MA": null,
          "rsi14": null,
          "macd": null,
          "macd_signal": null,
          "macd_hist": null,
          "macd_cross": null
        },
        "daily": {
          "close_above_sma36": false,
          "dist_to_36MA": -0.05400726119047045,
          "rsi14": 45.018268674706434,
          "macd": -1.614648350170441,
          "macd_signal": -1.5868600901758736,
          "macd_hist": -0.027788259994567355,
          "macd_cross": false
        },
        "weekly": {
          "close_above_sma36": false,
          "dist_to_36MA": -0.02505940764643125,
          "rsi14": 48.43365293726138,
          "macd": 1.488470143450158,
          "macd_signal": 3.7355105196213603,
          "macd_hist": -2.2470403761712023,
          "macd_cross": false
        },
        "monthly": {
          "close_above_sma36": true,
          "dist_to_36MA": 0.6850829742136114,
          "rsi14": 63.18162962690184,
          "macd": 15.170210852614403,
          "macd_signal": 13.689475014065634,
          "macd_hist": 1.4807358385487692,
          "macd_cross": false
        }
      }
    },
    {
      "ticker": "GDXJ",
      "display_name": "Junior gull",
      "symbol_label": "GDXJ",
      "category_title": "4. Edelmetaller",
      "is_52w_high": false,
      "is_52w_low": false,
      "52w_high": 156.19000244140625,
      "52w_low": 62.773780822753906,
      "dist_to_36WMA": null,
      "dist_to_36MMA": null,
      "weekly_close_count_above_36WMA": null,
      "gdx_gld_ratio_vs_50dma": null,
      "sil_slv_ratio_vs_50dma": null,
      "vol20_up_ok": null,
      "frames": {
        "hourly": {
          "close_above_sma36": null,
          "dist_to_36MA": null,
          "rsi14": null,
          "macd": null,
          "macd_signal": null,
          "macd_hist": null,
          "macd_cross": null
        },
        "daily": {
          "close_above_sma36": false,
          "dist_to_36MA": -0.050965182368001204,
          "rsi14": 45.80111342553099,
          "macd": -2.0935406067649467,
          "macd_signal": -2.0442748027287454,
          "macd_hist": -0.04926580403620129,
          "macd_cross": false
        },
        "weekly": {
          "close_above_sma36": false,
          "dist_to_36MA": -0.014694158383729871,
          "rsi14": 49.00150373145609,
          "macd": 2.4448825823221796,
          "macd_signal": 5.424074302997305,
          "macd_hist": -2.979191720675125,
          "macd_cross": false
        },
        "monthly": {
          "close_above_sma36": true,
          "dist_to_36MA": 0.7701676923526656,
          "rsi14": 63.00749535056595,
          "macd": 21.14892014992398,
          "macd_signal": 18.794369527217864,
          "macd_hist": 2.3545506227061175,
          "macd_cross": false
        }
      }
    },
    {
      "ticker": "SIL",
      "display_name": "Solv miners",
      "symbol_label": "SIL",
      "category_title": "4. Edelmetaller",
      "is_52w_high": false,
      "is_52w_low": false,
      "52w_high": 118.02999877929688,
      "52w_low": 42.62000274658203,
      "dist_to_36WMA": null,
      "dist_to_36MMA": null,
      "weekly_close_count_above_36WMA": null,
      "gdx_gld_ratio_vs_50dma": null,
      "sil_slv_ratio_vs_50dma": null,
      "vol20_up_ok": null,
      "frames": {
        "hourly": {
          "close_above_sma36": null,
          "dist_to_36MA": null,
          "rsi14": null,
          "macd": null,
          "macd_signal": null,
          "macd_hist": null,
          "macd_cross": null
        },
        "daily": {
          "close_above_sma36": false,
          "dist_to_36MA": -0.02375090212885969,
          "rsi14": 48.419352114256135,
          "macd": -0.8385161027097752,
          "macd_signal": -0.7573629051237182,
          "macd_hist": -0.08115319758605699,
          "macd_cross": false
        },
        "weekly": {
          "close_above_sma36": true,
          "dist_to_36MA": 0.0471895332523196,
          "rsi14": 51.46094625047783,
          "macd": 3.2902908050754434,
          "macd_signal": 5.176337581428859,
          "macd_hist": -1.8860467763534157,
          "macd_cross": false
        },
        "monthly": {
          "close_above_sma36": true,
          "dist_to_36MA": 0.8966890055759277,
          "rsi14": 65.32660847924207,
          "macd": 16.672896325655486,
          "macd_signal": 14.041156509927179,
          "macd_hist": 2.6317398157283076,
          "macd_cross": false
        }
      }
    },
    {
      "ticker": "SILJ",
      "display_name": "Junior solv",
      "symbol_label": "SILJ",
      "category_title": "4. Edelmetaller",
      "is_52w_high": false,
      "is_52w_low": false,
      "52w_high": 40.29999923706055,
      "52w_low": 12.818825721740723,
      "dist_to_36WMA": null,
      "dist_to_36MMA": null,
      "weekly_close_count_above_36WMA": null,
      "gdx_gld_ratio_vs_50dma": null,
      "sil_slv_ratio_vs_50dma": null,
      "vol20_up_ok": null,
      "frames": {
        "hourly": {
          "close_above_sma36": null,
          "dist_to_36MA": null,
          "rsi14": null,
          "macd": null,
          "macd_signal": null,
          "macd_hist": null,
          "macd_cross": null
        },
        "daily": {
          "close_above_sma36": false,
          "dist_to_36MA": -0.009123641799854058,
          "rsi14": 50.04036599914078,
          "macd": -0.23496849323677793,
          "macd_signal": -0.2466325817854921,
          "macd_hist": 0.011664088548714174,
          "macd_cross": true
        },
        "weekly": {
          "close_above_sma36": true,
          "dist_to_36MA": 0.04859489189813436,
          "rsi14": 51.89228386983172,
          "macd": 1.0455375015685675,
          "macd_signal": 1.703568705091766,
          "macd_hist": -0.6580312035231985,
          "macd_cross": false
        },
        "monthly": {
          "close_above_sma36": true,
          "dist_to_36MA": 0.9229644123617649,
          "rsi14": 65.27499699574616,
          "macd": 5.599145746414752,
          "macd_signal": 4.628589404940817,
          "macd_hist": 0.9705563414739355,
          "macd_cross": false
        }
      }
    },
    {
      "ticker": "PPLT",
      "display_name": "Platina",
      "symbol_label": "PPLT",
      "category_title": "4. Edelmetaller",
      "is_52w_high": false,
      "is_52w_low": false,
      "52w_high": 25.225000381469727,
      "52w_low": 9.675000190734863,
      "dist_to_36WMA": null,
      "dist_to_36MMA": null,
      "weekly_close_count_above_36WMA": null,
      "gdx_gld_ratio_vs_50dma": null,
      "sil_slv_ratio_vs_50dma": null,
      "vol20_up_ok": null,
      "frames": {
        "hourly": {
          "close_above_sma36": null,
          "dist_to_36MA": null,
          "rsi14": null,
          "macd": null,
          "macd_signal": null,
          "macd_hist": null,
          "macd_cross": null
        },
        "daily": {
          "close_above_sma36": false,
          "dist_to_36MA": -0.043640519701207504,
          "rsi14": 42.928139598172486,
          "macd": -0.2583329996191317,
          "macd_signal": -0.18169083841343497,
          "macd_hist": -0.07664216120569672,
          "macd_cross": false
        },
        "weekly": {
          "close_above_sma36": false,
          "dist_to_36MA": -0.016496575260076245,
          "rsi14": 48.6516014408662,
          "macd": 0.2551036227485888,
          "macd_signal": 0.6375534359236765,
          "macd_hist": -0.38244981317508775,
          "macd_cross": false
        },
        "monthly": {
          "close_above_sma36": true,
          "dist_to_36MA": 0.520296092346898,
          "rsi14": 64.80250019925808,
          "macd": 2.464842548733504,
          "macd_signal": 2.1027255525519575,
          "macd_hist": 0.36211699618154647,
          "macd_cross": false
        }
      }
    },
    {
      "ticker": "PALL",
      "display_name": "Palladium",
      "symbol_label": "PALL",
      "category_title": "4. Edelmetaller",
      "is_52w_high": false,
      "is_52w_low": false,
      "52w_high": 37.18199920654297,
      "52w_low": 17.756000518798828,
      "dist_to_36WMA": null,
      "dist_to_36MMA": null,
      "weekly_close_count_above_36WMA": null,
      "gdx_gld_ratio_vs_50dma": null,
      "sil_slv_ratio_vs_50dma": null,
      "vol20_up_ok": null,
      "frames": {
        "hourly": {
          "close_above_sma36": null,
          "dist_to_36MA": null,
          "rsi14": null,
          "macd": null,
          "macd_signal": null,
          "macd_hist": null,
          "macd_cross": null
        },
        "daily": {
          "close_above_sma36": false,
          "dist_to_36MA": -0.07224588631480502,
          "rsi14": 39.629907324655306,
          "macd": -0.7162154361385049,
          "macd_signal": -0.6454161642140318,
          "macd_hist": -0.0707992719244731,
          "macd_cross": false
        },
        "weekly": {
          "close_above_sma36": false,
          "dist_to_36MA": -0.11865143255106796,
          "rsi14": 42.87083253458941,
          "macd": -0.591310501823294,
          "macd_signal": 0.09185753275218886,
          "macd_hist": -0.6831680345754829,
          "macd_cross": false
        },
        "monthly": {
          "close_above_sma36": true,
          "dist_to_36MA": 0.16600938407679924,
          "rsi14": 51.11277457147775,
          "macd": 1.2897596276973715,
          "macd_signal": 0.7401961968542763,
          "macd_hist": 0.5495634308430952,
          "macd_cross": false
        }
      }
    },
    {
      "ticker": "URA",
      "display_name": "Uranium ETF",
      "symbol_label": "URA",
      "category_title": "5. Uranium & Energiomstilling",
      "is_52w_high": false,
      "is_52w_low": false,
      "52w_high": 61.810001373291016,
      "52w_low": 30.417943954467773,
      "dist_to_36WMA": null,
      "dist_to_36MMA": null,
      "weekly_close_count_above_36WMA": null,
      "gdx_gld_ratio_vs_50dma": null,
      "sil_slv_ratio_vs_50dma": null,
      "vol20_up_ok": null,
      "frames": {
        "hourly": {
          "close_above_sma36": null,
          "dist_to_36MA": null,
          "rsi14": null,
          "macd": null,
          "macd_signal": null,
          "macd_hist": null,
          "macd_cross": null
        },
        "daily": {
          "close_above_sma36": false,
          "dist_to_36MA": -0.05145113629116641,
          "rsi14": 46.229104618802324,
          "macd": -0.9369621665873424,
          "macd_signal": -0.8405390308789692,
          "macd_hist": -0.09642313570837324,
          "macd_cross": false
        },
        "weekly": {
          "close_above_sma36": true,
          "dist_to_36MA": 0.018186474604378618,
          "rsi14": 51.45762766243726,
          "macd": 1.397469770804726,
          "macd_signal": 2.014808293383923,
          "macd_hist": -0.617338522579197,
          "macd_cross": false
        },
        "monthly": {
          "close_above_sma36": true,
          "dist_to_36MA": 0.5109190432955918,
          "rsi14": 61.013627569743,
          "macd": 7.299267139062508,
          "macd_signal": 6.501203642926279,
          "macd_hist": 0.798063496136229,
          "macd_cross": false
        }
      }
    },
    {
      "ticker": "URNM",
      "display_name": "Uranium miners",
      "symbol_label": "URNM",
      "category_title": "5. Uranium & Energiomstilling",
      "is_52w_high": false,
      "is_52w_low": false,
      "52w_high": 83.98999786376953,
      "52w_low": 38.17708206176758,
      "dist_to_36WMA": null,
      "dist_to_36MMA": null,
      "weekly_close_count_above_36WMA": null,
      "gdx_gld_ratio_vs_50dma": null,
      "sil_slv_ratio_vs_50dma": null,
      "vol20_up_ok": null,
      "frames": {
        "hourly": {
          "close_above_sma36": null,
          "dist_to_36MA": null,
          "rsi14": null,
          "macd": null,
          "macd_signal": null,
          "macd_hist": null,
          "macd_cross": null
        },
        "daily": {
          "close_above_sma36": false,
          "dist_to_36MA": -0.05602828564109674,
          "rsi14": 45.99631104059738,
          "macd": -1.4998496912681034,
          "macd_signal": -1.604259392207451,
          "macd_hist": 0.10440970093934765,
          "macd_cross": true
        },
        "weekly": {
          "close_above_sma36": false,
          "dist_to_36MA": -0.015640050043388695,
          "rsi14": 48.65328929218917,
          "macd": 0.7165139086603531,
          "macd_signal": 1.9517834525178899,
          "macd_hist": -1.2352695438575367,
          "macd_cross": false
        },
        "monthly": {
          "close_above_sma36": true,
          "dist_to_36MA": 0.27088877577110676,
          "rsi14": 56.75533278294367,
          "macd": 6.888061112755068,
          "macd_signal": 6.062384591577768,
          "macd_hist": 0.8256765211773001,
          "macd_cross": false
        }
      }
    },
    {
      "ticker": "NLR",
      "display_name": "Nuclear energy",
      "symbol_label": "NLR",
      "category_title": "5. Uranium & Energiomstilling",
      "is_52w_high": false,
      "is_52w_low": false,
      "52w_high": 164.3699951171875,
      "52w_low": 94.6313705444336,
      "dist_to_36WMA": null,
      "dist_to_36MMA": null,
      "weekly_close_count_above_36WMA": null,
      "gdx_gld_ratio_vs_50dma": null,
      "sil_slv_ratio_vs_50dma": null,
      "vol20_up_ok": null,
      "frames": {
        "hourly": {
          "close_above_sma36": null,
          "dist_to_36MA": null,
          "rsi14": null,
          "macd": null,
          "macd_signal": null,
          "macd_hist": null,
          "macd_cross": null
        },
        "daily": {
          "close_above_sma36": false,
          "dist_to_36MA": -0.05172495411344848,
          "rsi14": 44.678106194407114,
          "macd": -2.365128767411079,
          "macd_signal": -2.3657294798585333,
          "macd_hist": 0.0006007124474542991,
          "macd_cross": true
        },
        "weekly": {
          "close_above_sma36": false,
          "dist_to_36MA": -0.04054371234922789,
          "rsi14": 47.248622034364665,
          "macd": 0.7324306531824618,
          "macd_signal": 2.4813900422274178,
          "macd_hist": -1.748959389044956,
          "macd_cross": false
        },
        "monthly": {
          "close_above_sma36": true,
          "dist_to_36MA": 0.3764221066958244,
          "rsi14": 58.822724226715856,
          "macd": 17.313558640809376,
          "macd_signal": 17.134045370940587,
          "macd_hist": 0.17951326986878868,
          "macd_cross": false
        }
      }
    },
    {
      "ticker": "ICLN",
      "display_name": "Clean energy",
      "symbol_label": "ICLN",
      "category_title": "5. Uranium & Energiomstilling",
      "is_52w_high": false,
      "is_52w_low": false,
      "52w_high": 23.56999969482422,
      "52w_low": 12.361300468444824,
      "dist_to_36WMA": null,
      "dist_to_36MMA": null,
      "weekly_close_count_above_36WMA": null,
      "gdx_gld_ratio_vs_50dma": null,
      "sil_slv_ratio_vs_50dma": null,
      "vol20_up_ok": null,
      "frames": {
        "hourly": {
          "close_above_sma36": null,
          "dist_to_36MA": null,
          "rsi14": null,
          "macd": null,
          "macd_signal": null,
          "macd_hist": null,
          "macd_cross": null
        },
        "daily": {
          "close_above_sma36": true,
          "dist_to_36MA": 0.09762202412268627,
          "rsi14": 65.10359601501472,
          "macd": 0.8482227938670235,
          "macd_signal": 0.7557170875118706,
          "macd_hist": 0.09250570635515287,
          "macd_cross": false
        },
        "weekly": {
          "close_above_sma36": true,
          "dist_to_36MA": 0.2589336048437817,
          "rsi14": 76.71633857065697,
          "macd": 1.626917823611059,
          "macd_signal": 1.2581771901754033,
          "macd_hist": 0.3687406334356558,
          "macd_cross": false
        },
        "monthly": {
          "close_above_sma36": true,
          "dist_to_36MA": 0.5585874231257258,
          "rsi14": 74.98821101592934,
          "macd": 1.9198340684720314,
          "macd_signal": 0.8325290250782951,
          "macd_hist": 1.0873050433937363,
          "macd_cross": false
        }
      }
    },
    {
      "ticker": "UUP",
      "display_name": "DXY",
      "symbol_label": "UUP",
      "category_title": "6. Valuta & Dollar",
      "is_52w_high": false,
      "is_52w_low": false,
      "52w_high": 27.979999542236328,
      "52w_low": 25.963289260864258,
      "dist_to_36WMA": null,
      "dist_to_36MMA": null,
      "weekly_close_count_above_36WMA": null,
      "gdx_gld_ratio_vs_50dma": null,
      "sil_slv_ratio_vs_50dma": null,
      "vol20_up_ok": null,
      "frames": {
        "hourly": {
          "close_above_sma36": null,
          "dist_to_36MA": null,
          "rsi14": null,
          "macd": null,
          "macd_signal": null,
          "macd_hist": null,
          "macd_cross": null
        },
        "daily": {
          "close_above_sma36": true,
          "dist_to_36MA": 0.008517337896526079,
          "rsi14": 58.482425592718,
          "macd": 0.06708183998298267,
          "macd_signal": 0.05822820429673455,
          "macd_hist": 0.00885363568624812,
          "macd_cross": false
        },
        "weekly": {
          "close_above_sma36": true,
          "dist_to_36MA": 0.01721574081811746,
          "rsi14": 58.25027852751043,
          "macd": 0.16586801644792004,
          "macd_signal": 0.15621141120586213,
          "macd_hist": 0.009656605242057914,
          "macd_cross": false
        },
        "monthly": {
          "close_above_sma36": true,
          "dist_to_36MA": 0.03873622181453937,
          "rsi14": 58.701463102890976,
          "macd": 0.40726136927444756,
          "macd_signal": 0.4222432195100878,
          "macd_hist": -0.014981850235640248,
          "macd_cross": false
        }
      }
    },
    {
      "ticker": "FXE",
      "display_name": "EUR/USD",
      "symbol_label": "FXE",
      "category_title": "6. Valuta & Dollar",
      "is_52w_high": false,
      "is_52w_low": false,
      "52w_high": 110.75480651855469,
      "52w_low": 104.02946472167969,
      "dist_to_36WMA": null,
      "dist_to_36MMA": null,
      "weekly_close_count_above_36WMA": null,
      "gdx_gld_ratio_vs_50dma": null,
      "sil_slv_ratio_vs_50dma": null,
      "vol20_up_ok": null,
      "frames": {
        "hourly": {
          "close_above_sma36": null,
          "dist_to_36MA": null,
          "rsi14": null,
          "macd": null,
          "macd_signal": null,
          "macd_hist": null,
          "macd_cross": null
        },
        "daily": {
          "close_above_sma36": false,
          "dist_to_36MA": -0.005320651267328818,
          "rsi14": 46.094080795128356,
          "macd": -0.1319682841248948,
          "macd_signal": -0.10315785122503995,
          "macd_hist": -0.028810432899854854,
          "macd_cross": false
        },
        "weekly": {
          "close_above_sma36": false,
          "dist_to_36MA": -0.0008216422242803637,
          "rsi14": 49.788343045061055,
          "macd": 0.15484131310242333,
          "macd_signal": 0.24683560791592996,
          "macd_hist": -0.09199429481350663,
          "macd_cross": false
        },
        "monthly": {
          "close_above_sma36": true,
          "dist_to_36MA": 0.06232016233883304,
          "rsi14": 58.90192476676899,
          "macd": 2.6535808846140014,
          "macd_signal": 2.6450747490237982,
          "macd_hist": 0.00850613559020319,
          "macd_cross": false
        }
      }
    },
    {
      "ticker": "FXY",
      "display_name": "JPY",
      "symbol_label": "FXY",
      "category_title": "6. Valuta & Dollar",
      "is_52w_high": false,
      "is_52w_low": false,
      "52w_high": 64.58000183105469,
      "52w_low": 57.2599983215332,
      "dist_to_36WMA": null,
      "dist_to_36MMA": null,
      "weekly_close_count_above_36WMA": null,
      "gdx_gld_ratio_vs_50dma": null,
      "sil_slv_ratio_vs_50dma": null,
      "vol20_up_ok": null,
      "frames": {
        "hourly": {
          "close_above_sma36": null,
          "dist_to_36MA": null,
          "rsi14": null,
          "macd": null,
          "macd_signal": null,
          "macd_hist": null,
          "macd_cross": null
        },
        "daily": {
          "close_above_sma36": false,
          "dist_to_36MA": -0.006316257827075862,
          "rsi14": 40.08836862811206,
          "macd": -0.11054340960534148,
          "macd_signal": -0.050994293556605674,
          "macd_hist": -0.059549116048735806,
          "macd_cross": false
        },
        "weekly": {
          "close_above_sma36": false,
          "dist_to_36MA": -0.021522778480771734,
          "rsi14": 40.64200455499895,
          "macd": -0.5488224700862645,
          "macd_signal": -0.6195468035540685,
          "macd_hist": 0.07072433346780405,
          "macd_cross": false
        },
        "monthly": {
          "close_above_sma36": false,
          "dist_to_36MA": -0.05911974840378989,
          "rsi14": 38.623048490487065,
          "macd": -1.7486471716205045,
          "macd_signal": -1.667327199290848,
          "macd_hist": -0.08131997232965649,
          "macd_cross": false
        }
      }
    },
    {
      "ticker": "CEW",
      "display_name": "EM Currencies",
      "symbol_label": "CEW",
      "category_title": "6. Valuta & Dollar",
      "is_52w_high": false,
      "is_52w_low": false,
      "52w_high": 19.59000015258789,
      "52w_low": 17.86878204345703,
      "dist_to_36WMA": null,
      "dist_to_36MMA": null,
      "weekly_close_count_above_36WMA": null,
      "gdx_gld_ratio_vs_50dma": null,
      "sil_slv_ratio_vs_50dma": null,
      "vol20_up_ok": null,
      "frames": {
        "hourly": {
          "close_above_sma36": null,
          "dist_to_36MA": null,
          "rsi14": null,
          "macd": null,
          "macd_signal": null,
          "macd_hist": null,
          "macd_cross": null
        },
        "daily": {
          "close_above_sma36": true,
          "dist_to_36MA": 0.0028457213962040763,
          "rsi14": 56.23011265556123,
          "macd": 0.021353513356842768,
          "macd_signal": 0.016296101294796632,
          "macd_hist": 0.005057412062046136,
          "macd_cross": false
        },
        "weekly": {
          "close_above_sma36": true,
          "dist_to_36MA": 0.023960404115489345,
          "rsi14": 60.80582172832245,
          "macd": 0.19001228148937344,
          "macd_signal": 0.20250152248396944,
          "macd_hist": -0.012489240994596001,
          "macd_cross": false
        },
        "monthly": {
          "close_above_sma36": true,
          "dist_to_36MA": 0.11667620662576011,
          "rsi14": 71.63703874016217,
          "macd": 0.7584997232113082,
          "macd_signal": 0.6891348335806207,
          "macd_hist": 0.06936488963068754,
          "macd_cross": false
        }
      }
    },
    {
      "ticker": "FXA",
      "display_name": "AUD",
      "symbol_label": "FXA",
      "category_title": "6. Valuta & Dollar",
      "is_52w_high": false,
      "is_52w_low": false,
      "52w_high": 71.72821807861328,
      "52w_low": 63.0718879699707,
      "dist_to_36WMA": null,
      "dist_to_36MMA": null,
      "weekly_close_count_above_36WMA": null,
      "gdx_gld_ratio_vs_50dma": null,
      "sil_slv_ratio_vs_50dma": null,
      "vol20_up_ok": null,
      "frames": {
        "hourly": {
          "close_above_sma36": null,
          "dist_to_36MA": null,
          "rsi14": null,
          "macd": null,
          "macd_signal": null,
          "macd_hist": null,
          "macd_cross": null
        },
        "daily": {
          "close_above_sma36": false,
          "dist_to_36MA": -0.0004379135161241291,
          "rsi14": 50.78716606238083,
          "macd": 0.07736501721072386,
          "macd_signal": 0.14365918099748082,
          "macd_hist": -0.06629416378675695,
          "macd_cross": false
        },
        "weekly": {
          "close_above_sma36": true,
          "dist_to_36MA": 0.047697336915100974,
          "rsi14": 62.89448466435506,
          "macd": 1.3061753112797163,
          "macd_signal": 1.3521909634761573,
          "macd_hist": -0.04601565219644099,
          "macd_cross": false
        },
        "monthly": {
          "close_above_sma36": true,
          "dist_to_36MA": 0.09968321081397108,
          "rsi14": 64.22001733478129,
          "macd": 1.8130680473983887,
          "macd_signal": 0.9866076242110766,
          "macd_hist": 0.826460423187312,
          "macd_cross": false
        }
      }
    },
    {
      "ticker": "BTC",
      "display_name": "BTC",
      "symbol_label": "BTC",
      "category_title": "7. Crypto & Volatilitet",
      "is_52w_high": false,
      "is_52w_low": false,
      "52w_high": 124752.53125,
      "52w_low": 62702.09765625,
      "dist_to_36WMA": null,
      "dist_to_36MMA": null,
      "weekly_close_count_above_36WMA": null,
      "gdx_gld_ratio_vs_50dma": null,
      "sil_slv_ratio_vs_50dma": null,
      "vol20_up_ok": null,
      "frames": {
        "hourly": {
          "close_above_sma36": null,
          "dist_to_36MA": null,
          "rsi14": null,
          "macd": null,
          "macd_signal": null,
          "macd_hist": null,
          "macd_cross": null
        },
        "daily": {
          "close_above_sma36": false,
          "dist_to_36MA": -0.09993527073972051,
          "rsi14": 26.546529541053786,
          "macd": -1638.809431322792,
          "macd_signal": -918.6170184926061,
          "macd_hist": -720.192412830186,
          "macd_cross": false
        },
        "weekly": {
          "close_above_sma36": false,
          "dist_to_36MA": -0.1751323149794228,
          "rsi14": 37.63541158988418,
          "macd": -4311.89019475739,
          "macd_signal": -5379.522079510358,
          "macd_hist": 1067.6318847529674,
          "macd_cross": false
        },
        "monthly": {
          "close_above_sma36": false,
          "dist_to_36MA": -0.051340590378861954,
          "rsi14": 45.3885376512056,
          "macd": 2346.4702546003246,
          "macd_signal": 7877.83599045858,
          "macd_hist": -5531.365735858256,
          "macd_cross": false
        }
      }
    },
    {
      "ticker": "ETHA",
      "display_name": "ETH",
      "symbol_label": "ETH",
      "category_title": "7. Crypto & Volatilitet",
      "is_52w_high": false,
      "is_52w_low": false,
      "52w_high": 4687.771484375,
      "52w_low": 1821.68310546875,
      "dist_to_36WMA": null,
      "dist_to_36MMA": null,
      "weekly_close_count_above_36WMA": null,
      "gdx_gld_ratio_vs_50dma": null,
      "sil_slv_ratio_vs_50dma": null,
      "vol20_up_ok": null,
      "frames": {
        "hourly": {
          "close_above_sma36": null,
          "dist_to_36MA": null,
          "rsi14": null,
          "macd": null,
          "macd_signal": null,
          "macd_hist": null,
          "macd_cross": null
        },
        "daily": {
          "close_above_sma36": false,
          "dist_to_36MA": -0.09700813585973073,
          "rsi14": 29.157606721455764,
          "macd": -68.42168710975375,
          "macd_signal": -61.18029349183471,
          "macd_hist": -7.241393617919037,
          "macd_cross": false
        },
        "weekly": {
          "close_above_sma36": false,
          "dist_to_36MA": -0.2713292091140068,
          "rsi14": 36.72706170486193,
          "macd": -232.8636124146201,
          "macd_signal": -253.63551313262235,
          "macd_hist": 20.771900718002257,
          "macd_cross": false
        },
        "monthly": {
          "close_above_sma36": false,
          "dist_to_36MA": -0.2716868018793615,
          "rsi14": 43.194654144766965,
          "macd": -126.42143382132372,
          "macd_signal": 43.91854767163686,
          "macd_hist": -170.3399814929606,
          "macd_cross": false
        }
      }
    },
    {
      "ticker": "VIXY",
      "display_name": "VIX",
      "symbol_label": "VIXY",
      "category_title": "7. Crypto & Volatilitet",
      "is_52w_high": false,
      "is_52w_low": false,
      "52w_high": 53.810001373291016,
      "52w_low": 23.290000915527344,
      "dist_to_36WMA": null,
      "dist_to_36MMA": null,
      "weekly_close_count_above_36WMA": null,
      "gdx_gld_ratio_vs_50dma": null,
      "sil_slv_ratio_vs_50dma": null,
      "vol20_up_ok": null,
      "frames": {
        "hourly": {
          "close_above_sma36": null,
          "dist_to_36MA": null,
          "rsi14": null,
          "macd": null,
          "macd_signal": null,
          "macd_hist": null,
          "macd_cross": null
        },
        "daily": {
          "close_above_sma36": false,
          "dist_to_36MA": -0.11740215545275762,
          "rsi14": 32.09252832171724,
          "macd": -1.3122271759010893,
          "macd_signal": -1.126536459155593,
          "macd_hist": -0.1856907167454962,
          "macd_cross": false
        },
        "weekly": {
          "close_above_sma36": false,
          "dist_to_36MA": -0.19750258072607832,
          "rsi14": 36.70370965167637,
          "macd": -2.114334862163453,
          "macd_signal": -1.6438115140694574,
          "macd_hist": -0.47052334809399565,
          "macd_cross": false
        },
        "monthly": {
          "close_above_sma36": false,
          "dist_to_36MA": -0.5095087571387152,
          "rsi14": 31.66711509648566,
          "macd": -35.292502107801056,
          "macd_signal": -46.61431191867425,
          "macd_hist": 11.32180981087319,
          "macd_cross": false
        }
      }
    }
  ],
  "news": {
    "nftrh": [
      {
        "title": "Protected: One Indicator the Broad Market Has Going For It",
        "link": "",
        "published": "2026-06-01T20:17:06+02:00"
      },
      {
        "title": "Protected: NFTRH+; A Bullish Sign for the Commodity/Resources Trades",
        "link": "",
        "published": "2026-06-01T18:35:29+02:00"
      },
      {
        "title": "Profitable Trades Have Come Too Easy",
        "link": "",
        "published": "2026-06-01T16:51:28+02:00"
      },
      {
        "title": "Notes From the Rabbit Hole, #917 (Public)",
        "link": "",
        "published": "2026-05-31T23:26:22+02:00"
      },
      {
        "title": "Protected: Notes From the Rabbit Hole, #917",
        "link": "",
        "published": "2026-05-31T16:58:43+02:00"
      }
    ],
    "northstar": []
  },
  "missing": []
}