[
  {
    "source": "NFTRH",
    "title": "Protected: NFTRH+; U.S. Market Internals & Indications",
    "url": "https://nftrh.com/2025/11/11/market-internals/",
    "published": "2025-11-11T18:22:25+00:00",
    "image": "news/NFTRH_Protected_NFTRH_U.S._Market_Internals_Indications.jpg"
  },
  {
    "source": "NFTRH",
    "title": "ATTN: NFTRH Subscribers; Yahoo email issue [w/ edit]",
    "url": "https://nftrh.com/2025/11/09/attn-nftrh-subscribers-yahoo-email-issue/",
    "published": "2025-11-09T19:19:05+00:00",
    "image": "news/NFTRH_ATTN_NFTRH_Subscribers_Yahoo_email_issue_w_edit_.jpg"
  },
  {
    "source": "NFTRH",
    "title": "Protected: Notes From the Rabbit Hole, #888",
    "url": "https://nftrh.com/2025/11/09/notes-from-the-rabbit-hole-888/",
    "published": "2025-11-09T17:42:37+00:00",
    "image": "news/NFTRH_Protected_Notes_From_the_Rabbit_Hole_888.jpg"
  },
  {
    "nftrh": [],
    "northstar": []
  }
]